<?xml version="1.0" encoding="utf-8"?><MPD xmlns="urn:mpeg:dash:schema:mpd:2011" profiles="urn:mpeg:dash:profile:full:2011" minBufferTime="PT1.5S" type="static" mediaPresentationDuration="PT1063S"><Period><AdaptationSet id="0" mimeType="video/mp4" startWithSAP="1" subsegmentAlignment="true" scanType="progressive"><Representation id="137" codecs="avc1.640028" bandwidth="2072239" width="1920" height="1080" maxPlayoutRate="1" frameRate="25"><BaseURL>https://r1---sn-ci5gup-qxas.googlevideo.com/videoplayback?expire=1625506969&amp;ei=OfDiYMPTE5KOmgfBs6LACA&amp;ip=122.161.68.8&amp;id=o-AJno_OyI_qSilg0pKp7jBgwanqzvHVJKPkIGZjQw22X8&amp;itag=137&amp;aitags=133%2C134%2C135%2C136%2C137%2C160%2C242%2C243%2C244%2C247%2C248%2C278&amp;source=youtube&amp;requiressl=yes&amp;mh=5j&amp;mm=31%2C26&amp;mn=sn-ci5gup-qxas%2Csn-cvh7knll&amp;ms=au%2Conr&amp;mv=m&amp;mvi=1&amp;pcm2cms=yes&amp;pl=20&amp;initcwndbps=1257500&amp;vprv=1&amp;mime=video%2Fmp4&amp;ns=ipuIFyzlt_lney8Fp0br1p8G&amp;gir=yes&amp;clen=93010571&amp;dur=1062.320&amp;lmt=1537380298381141&amp;mt=1625485010&amp;fvip=1&amp;keepalive=yes&amp;fexp=24001373%2C24007246&amp;c=WEB&amp;n=INvp8Xl-NYS_WS&amp;sparams=expire%2Cei%2Cip%2Cid%2Caitags%2Csource%2Crequiressl%2Cvprv%2Cmime%2Cns%2Cgir%2Cclen%2Cdur%2Clmt&amp;sig=AOq0QJ8wRQIgRqPUJgAN3pih1fnP8qwpwGvToqySFMV2OltK4TRVkEkCIQCIMoLSQk2mBeUQpun8ERMwpTN13JSgjz4udo7a5DPhHA%3D%3D&amp;lsparams=mh%2Cmm%2Cmn%2Cms%2Cmv%2Cmvi%2Cpcm2cms%2Cpl%2Cinitcwndbps&amp;lsig=AG3C_xAwRgIhAIe-ZkVUNAh3_cNjBSy8EhGUmtNSIeH_vTTbMWzKvqVeAiEAvvO7q0GQykvj21KEthsU55H2RzLG6RpIt-jt-YAhQP0%3D&amp;ratebypass=yes</BaseURL><SegmentBase indexRange="716-3255"><Initialization range="0-715"/></SegmentBase></Representation><Representation id="136" codecs="avc1.4d401f" bandwidth="1023928" width="1280" height="720" maxPlayoutRate="1" frameRate="25"><BaseURL>https://r1---sn-ci5gup-qxas.googlevideo.com/videoplayback?expire=1625506969&amp;ei=OfDiYMPTE5KOmgfBs6LACA&amp;ip=122.161.68.8&amp;id=o-AJno_OyI_qSilg0pKp7jBgwanqzvHVJKPkIGZjQw22X8&amp;itag=136&amp;aitags=133%2C134%2C135%2C136%2C137%2C160%2C242%2C243%2C244%2C247%2C248%2C278&amp;source=youtube&amp;requiressl=yes&amp;mh=5j&amp;mm=31%2C26&amp;mn=sn-ci5gup-qxas%2Csn-cvh7knll&amp;ms=au%2Conr&amp;mv=m&amp;mvi=1&amp;pcm2cms=yes&amp;pl=20&amp;initcwndbps=1257500&amp;vprv=1&amp;mime=video%2Fmp4&amp;ns=ipuIFyzlt_lney8Fp0br1p8G&amp;gir=yes&amp;clen=57190754&amp;dur=1062.320&amp;lmt=1537380112009324&amp;mt=1625485010&amp;fvip=1&amp;keepalive=yes&amp;fexp=24001373%2C24007246&amp;c=WEB&amp;n=INvp8Xl-NYS_WS&amp;sparams=expire%2Cei%2Cip%2Cid%2Caitags%2Csource%2Crequiressl%2Cvprv%2Cmime%2Cns%2Cgir%2Cclen%2Cdur%2Clmt&amp;sig=AOq0QJ8wRgIhAJrUuxZqDqCPKeaQDmS5o4BlA8BEteO5EXUfU6diMayOAiEAi7jHN7pyLZP_4xsQhVjfD-5PUNIQOI9Ss92jx5ADOvA%3D&amp;lsparams=mh%2Cmm%2Cmn%2Cms%2Cmv%2Cmvi%2Cpcm2cms%2Cpl%2Cinitcwndbps&amp;lsig=AG3C_xAwRgIhAIe-ZkVUNAh3_cNjBSy8EhGUmtNSIeH_vTTbMWzKvqVeAiEAvvO7q0GQykvj21KEthsU55H2RzLG6RpIt-jt-YAhQP0%3D&amp;ratebypass=yes</BaseURL><SegmentBase indexRange="714-3253"><Initialization range="0-713"/></SegmentBase></Representation><Representation id="135" codecs="avc1.4d401e" bandwidth="534078" width="854" height="480" maxPlayoutRate="1" frameRate="25"><BaseURL>https://r1---sn-ci5gup-qxas.googlevideo.com/videoplayback?expire=1625506969&amp;ei=OfDiYMPTE5KOmgfBs6LACA&amp;ip=122.161.68.8&amp;id=o-AJno_OyI_qSilg0pKp7jBgwanqzvHVJKPkIGZjQw22X8&amp;itag=135&amp;aitags=133%2C134%2C135%2C136%2C137%2C160%2C242%2C243%2C244%2C247%2C248%2C278&amp;source=youtube&amp;requiressl=yes&amp;mh=5j&amp;mm=31%2C26&amp;mn=sn-ci5gup-qxas%2Csn-cvh7knll&amp;ms=au%2Conr&amp;mv=m&amp;mvi=1&amp;pcm2cms=yes&amp;pl=20&amp;initcwndbps=1257500&amp;vprv=1&amp;mime=video%2Fmp4&amp;ns=ipuIFyzlt_lney8Fp0br1p8G&amp;gir=yes&amp;clen=36245242&amp;dur=1062.320&amp;lmt=1537378672121554&amp;mt=1625485010&amp;fvip=1&amp;keepalive=yes&amp;fexp=24001373%2C24007246&amp;c=WEB&amp;n=INvp8Xl-NYS_WS&amp;sparams=expire%2Cei%2Cip%2Cid%2Caitags%2Csource%2Crequiressl%2Cvprv%2Cmime%2Cns%2Cgir%2Cclen%2Cdur%2Clmt&amp;sig=AOq0QJ8wRQIgF90PTESmsOgIMteU98Ov-fpW8DmQTtoc-CXZQ8EBI3gCIQDEW_onoY1xojAWSx0U2zj8WA3V6ISRQtjU2A1pzBEsUQ%3D%3D&amp;lsparams=mh%2Cmm%2Cmn%2Cms%2Cmv%2Cmvi%2Cpcm2cms%2Cpl%2Cinitcwndbps&amp;lsig=AG3C_xAwRgIhAIe-ZkVUNAh3_cNjBSy8EhGUmtNSIeH_vTTbMWzKvqVeAiEAvvO7q0GQykvj21KEthsU55H2RzLG6RpIt-jt-YAhQP0%3D&amp;ratebypass=yes</BaseURL><SegmentBase indexRange="715-3254"><Initialization range="0-714"/></SegmentBase></Representation><Representation id="134" codecs="avc1.4d401e" bandwidth="349958" width="640" height="360" maxPlayoutRate="1" frameRate="25"><BaseURL>https://r1---sn-ci5gup-qxas.googlevideo.com/videoplayback?expire=1625506969&amp;ei=OfDiYMPTE5KOmgfBs6LACA&amp;ip=122.161.68.8&amp;id=o-AJno_OyI_qSilg0pKp7jBgwanqzvHVJKPkIGZjQw22X8&amp;itag=134&amp;aitags=133%2C134%2C135%2C136%2C137%2C160%2C242%2C243%2C244%2C247%2C248%2C278&amp;source=youtube&amp;requiressl=yes&amp;mh=5j&amp;mm=31%2C26&amp;mn=sn-ci5gup-qxas%2Csn-cvh7knll&amp;ms=au%2Conr&amp;mv=m&amp;mvi=1&amp;pcm2cms=yes&amp;pl=20&amp;initcwndbps=1257500&amp;vprv=1&amp;mime=video%2Fmp4&amp;ns=ipuIFyzlt_lney8Fp0br1p8G&amp;gir=yes&amp;clen=22807895&amp;dur=1062.320&amp;lmt=1537378655050941&amp;mt=1625485010&amp;fvip=1&amp;keepalive=yes&amp;fexp=24001373%2C24007246&amp;c=WEB&amp;n=INvp8Xl-NYS_WS&amp;sparams=expire%2Cei%2Cip%2Cid%2Caitags%2Csource%2Crequiressl%2Cvprv%2Cmime%2Cns%2Cgir%2Cclen%2Cdur%2Clmt&amp;sig=AOq0QJ8wRgIhAK3ntkmjxVariYwhKcStDDOLuMy_4yIvNO96gZr00BX7AiEAzZGWPiyBeprfl7mqF8EBSaTEiniEvKLhx0TSrT3R3bI%3D&amp;lsparams=mh%2Cmm%2Cmn%2Cms%2Cmv%2Cmvi%2Cpcm2cms%2Cpl%2Cinitcwndbps&amp;lsig=AG3C_xAwRgIhAIe-ZkVUNAh3_cNjBSy8EhGUmtNSIeH_vTTbMWzKvqVeAiEAvvO7q0GQykvj21KEthsU55H2RzLG6RpIt-jt-YAhQP0%3D&amp;ratebypass=yes</BaseURL><SegmentBase indexRange="715-3254"><Initialization range="0-714"/></SegmentBase></Representation><Representation id="133" codecs="avc1.4d4015" bandwidth="164092" width="426" height="240" maxPlayoutRate="1" frameRate="25"><BaseURL>https://r1---sn-ci5gup-qxas.googlevideo.com/videoplayback?expire=1625506969&amp;ei=OfDiYMPTE5KOmgfBs6LACA&amp;ip=122.161.68.8&amp;id=o-AJno_OyI_qSilg0pKp7jBgwanqzvHVJKPkIGZjQw22X8&amp;itag=133&amp;aitags=133%2C134%2C135%2C136%2C137%2C160%2C242%2C243%2C244%2C247%2C248%2C278&amp;source=youtube&amp;requiressl=yes&amp;mh=5j&amp;mm=31%2C26&amp;mn=sn-ci5gup-qxas%2Csn-cvh7knll&amp;ms=au%2Conr&amp;mv=m&amp;mvi=1&amp;pcm2cms=yes&amp;pl=20&amp;initcwndbps=1257500&amp;vprv=1&amp;mime=video%2Fmp4&amp;ns=ipuIFyzlt_lney8Fp0br1p8G&amp;gir=yes&amp;clen=11338742&amp;dur=1062.320&amp;lmt=1537378656959095&amp;mt=1625485010&amp;fvip=1&amp;keepalive=yes&amp;fexp=24001373%2C24007246&amp;c=WEB&amp;n=INvp8Xl-NYS_WS&amp;sparams=expire%2Cei%2Cip%2Cid%2Caitags%2Csource%2Crequiressl%2Cvprv%2Cmime%2Cns%2Cgir%2Cclen%2Cdur%2Clmt&amp;sig=AOq0QJ8wRQIhALjxA2DNB584AEhPF86PU1JS8qSpm8_3ZkX3XX7Ncu0iAiBWFbqaLuk_3zR_yGrFc0cxl6yqlTSblWh71XKvXmqNVA%3D%3D&amp;lsparams=mh%2Cmm%2Cmn%2Cms%2Cmv%2Cmvi%2Cpcm2cms%2Cpl%2Cinitcwndbps&amp;lsig=AG3C_xAwRgIhAIe-ZkVUNAh3_cNjBSy8EhGUmtNSIeH_vTTbMWzKvqVeAiEAvvO7q0GQykvj21KEthsU55H2RzLG6RpIt-jt-YAhQP0%3D&amp;ratebypass=yes</BaseURL><SegmentBase indexRange="714-3253"><Initialization range="0-713"/></SegmentBase></Representation><Representation id="160" codecs="avc1.4d400c" bandwidth="76923" width="256" height="144" maxPlayoutRate="1" frameRate="25"><BaseURL>https://r1---sn-ci5gup-qxas.googlevideo.com/videoplayback?expire=1625506969&amp;ei=OfDiYMPTE5KOmgfBs6LACA&amp;ip=122.161.68.8&amp;id=o-AJno_OyI_qSilg0pKp7jBgwanqzvHVJKPkIGZjQw22X8&amp;itag=160&amp;aitags=133%2C134%2C135%2C136%2C137%2C160%2C242%2C243%2C244%2C247%2C248%2C278&amp;source=youtube&amp;requiressl=yes&amp;mh=5j&amp;mm=31%2C26&amp;mn=sn-ci5gup-qxas%2Csn-cvh7knll&amp;ms=au%2Conr&amp;mv=m&amp;mvi=1&amp;pcm2cms=yes&amp;pl=20&amp;initcwndbps=1257500&amp;vprv=1&amp;mime=video%2Fmp4&amp;ns=ipuIFyzlt_lney8Fp0br1p8G&amp;gir=yes&amp;clen=4591529&amp;dur=1062.320&amp;lmt=1537378652965885&amp;mt=1625485010&amp;fvip=1&amp;keepalive=yes&amp;fexp=24001373%2C24007246&amp;c=WEB&amp;n=INvp8Xl-NYS_WS&amp;sparams=expire%2Cei%2Cip%2Cid%2Caitags%2Csource%2Crequiressl%2Cvprv%2Cmime%2Cns%2Cgir%2Cclen%2Cdur%2Clmt&amp;sig=AOq0QJ8wRgIhAMGza98CdHePCApYdyTx5JShOEdXjRVMJIFyNI07h_3FAiEAvBAJEY3kjrxTs5t02jb9SIunSjYf5xtXXGPSLM7S9tQ%3D&amp;lsparams=mh%2Cmm%2Cmn%2Cms%2Cmv%2Cmvi%2Cpcm2cms%2Cpl%2Cinitcwndbps&amp;lsig=AG3C_xAwRgIhAIe-ZkVUNAh3_cNjBSy8EhGUmtNSIeH_vTTbMWzKvqVeAiEAvvO7q0GQykvj21KEthsU55H2RzLG6RpIt-jt-YAhQP0%3D&amp;ratebypass=yes</BaseURL><SegmentBase indexRange="713-3252"><Initialization range="0-712"/></SegmentBase></Representation></AdaptationSet><AdaptationSet id="1" mimeType="video/webm" startWithSAP="1" subsegmentAlignment="true" scanType="progressive"><Representation id="248" codecs="vp9" bandwidth="2098256" width="1920" height="1080" maxPlayoutRate="1" frameRate="25"><BaseURL>https://r1---sn-ci5gup-qxas.googlevideo.com/videoplayback?expire=1625506969&amp;ei=OfDiYMPTE5KOmgfBs6LACA&amp;ip=122.161.68.8&amp;id=o-AJno_OyI_qSilg0pKp7jBgwanqzvHVJKPkIGZjQw22X8&amp;itag=248&amp;aitags=133%2C134%2C135%2C136%2C137%2C160%2C242%2C243%2C244%2C247%2C248%2C278&amp;source=youtube&amp;requiressl=yes&amp;mh=5j&amp;mm=31%2C26&amp;mn=sn-ci5gup-qxas%2Csn-cvh7knll&amp;ms=au%2Conr&amp;mv=m&amp;mvi=1&amp;pcm2cms=yes&amp;pl=20&amp;initcwndbps=1257500&amp;vprv=1&amp;mime=video%2Fwebm&amp;ns=ipuIFyzlt_lney8Fp0br1p8G&amp;gir=yes&amp;clen=100026805&amp;dur=1062.320&amp;lmt=1537381443477972&amp;mt=1625485010&amp;fvip=1&amp;keepalive=yes&amp;fexp=24001373%2C24007246&amp;c=WEB&amp;n=INvp8Xl-NYS_WS&amp;sparams=expire%2Cei%2Cip%2Cid%2Caitags%2Csource%2Crequiressl%2Cvprv%2Cmime%2Cns%2Cgir%2Cclen%2Cdur%2Clmt&amp;sig=AOq0QJ8wRQIgaorjodkbVkUR_5OoNNecm-hktXuFrpTZO98X91qWWXICIQCeBuX3FfKtw_clzVWAXSLvbO0lz9Q3y4XpQYi3JG8oIw%3D%3D&amp;lsparams=mh%2Cmm%2Cmn%2Cms%2Cmv%2Cmvi%2Cpcm2cms%2Cpl%2Cinitcwndbps&amp;lsig=AG3C_xAwRgIhAIe-ZkVUNAh3_cNjBSy8EhGUmtNSIeH_vTTbMWzKvqVeAiEAvvO7q0GQykvj21KEthsU55H2RzLG6RpIt-jt-YAhQP0%3D&amp;ratebypass=yes</BaseURL><SegmentBase indexRange="220-3932"><Initialization range="0-219"/></SegmentBase></Representation><Representation id="247" codecs="vp9" bandwidth="1032865" width="1280" height="720" maxPlayoutRate="1" frameRate="25"><BaseURL>https://r1---sn-ci5gup-qxas.googlevideo.com/videoplayback?expire=1625506969&amp;ei=OfDiYMPTE5KOmgfBs6LACA&amp;ip=122.161.68.8&amp;id=o-AJno_OyI_qSilg0pKp7jBgwanqzvHVJKPkIGZjQw22X8&amp;itag=247&amp;aitags=133%2C134%2C135%2C136%2C137%2C160%2C242%2C243%2C244%2C247%2C248%2C278&amp;source=youtube&amp;requiressl=yes&amp;mh=5j&amp;mm=31%2C26&amp;mn=sn-ci5gup-qxas%2Csn-cvh7knll&amp;ms=au%2Conr&amp;mv=m&amp;mvi=1&amp;pcm2cms=yes&amp;pl=20&amp;initcwndbps=1257500&amp;vprv=1&amp;mime=video%2Fwebm&amp;ns=ipuIFyzlt_lney8Fp0br1p8G&amp;gir=yes&amp;clen=64743042&amp;dur=1062.320&amp;lmt=1537379315271883&amp;mt=1625485010&amp;fvip=1&amp;keepalive=yes&amp;fexp=24001373%2C24007246&amp;c=WEB&amp;n=INvp8Xl-NYS_WS&amp;sparams=expire%2Cei%2Cip%2Cid%2Caitags%2Csource%2Crequiressl%2Cvprv%2Cmime%2Cns%2Cgir%2Cclen%2Cdur%2Clmt&amp;sig=AOq0QJ8wRgIhALIhsTsLoqBET0Yq8v0Ovm4cZDNdIXzO3q7ccqdMkTh-AiEA3LMfy7TS8elc5_BRKPo22Br95WjacUudJY5mMAUOumQ%3D&amp;lsparams=mh%2Cmm%2Cmn%2Cms%2Cmv%2Cmvi%2Cpcm2cms%2Cpl%2Cinitcwndbps&amp;lsig=AG3C_xAwRgIhAIe-ZkVUNAh3_cNjBSy8EhGUmtNSIeH_vTTbMWzKvqVeAiEAvvO7q0GQykvj21KEthsU55H2RzLG6RpIt-jt-YAhQP0%3D&amp;ratebypass=yes</BaseURL><SegmentBase indexRange="220-3917"><Initialization range="0-219"/></SegmentBase></Representation><Representation id="244" codecs="vp9" bandwidth="661885" width="854" height="480" maxPlayoutRate="1" frameRate="25"><BaseURL>https://r1---sn-ci5gup-qxas.googlevideo.com/videoplayback?expire=1625506969&amp;ei=OfDiYMPTE5KOmgfBs6LACA&amp;ip=122.161.68.8&amp;id=o-AJno_OyI_qSilg0pKp7jBgwanqzvHVJKPkIGZjQw22X8&amp;itag=244&amp;aitags=133%2C134%2C135%2C136%2C137%2C160%2C242%2C243%2C244%2C247%2C248%2C278&amp;source=youtube&amp;requiressl=yes&amp;mh=5j&amp;mm=31%2C26&amp;mn=sn-ci5gup-qxas%2Csn-cvh7knll&amp;ms=au%2Conr&amp;mv=m&amp;mvi=1&amp;pcm2cms=yes&amp;pl=20&amp;initcwndbps=1257500&amp;vprv=1&amp;mime=video%2Fwebm&amp;ns=ipuIFyzlt_lney8Fp0br1p8G&amp;gir=yes&amp;clen=47846888&amp;dur=1062.320&amp;lmt=1537379596603642&amp;mt=1625485010&amp;fvip=1&amp;keepalive=yes&amp;fexp=24001373%2C24007246&amp;c=WEB&amp;n=INvp8Xl-NYS_WS&amp;sparams=expire%2Cei%2Cip%2Cid%2Caitags%2Csource%2Crequiressl%2Cvprv%2Cmime%2Cns%2Cgir%2Cclen%2Cdur%2Clmt&amp;sig=AOq0QJ8wRAIgFR67-CE66_rWV_gFgENWkBriOhXEPSuK7VzDzFAEZ2ECIHl-hrP8jcMsaYPVCjGRWCQ4g1HUB7OMb5K5UwnYPQ0x&amp;lsparams=mh%2Cmm%2Cmn%2Cms%2Cmv%2Cmvi%2Cpcm2cms%2Cpl%2Cinitcwndbps&amp;lsig=AG3C_xAwRgIhAIe-ZkVUNAh3_cNjBSy8EhGUmtNSIeH_vTTbMWzKvqVeAiEAvvO7q0GQykvj21KEthsU55H2RzLG6RpIt-jt-YAhQP0%3D&amp;ratebypass=yes</BaseURL><SegmentBase indexRange="220-3905"><Initialization range="0-219"/></SegmentBase></Representation><Representation id="243" codecs="vp9" bandwidth="373299" width="640" height="360" maxPlayoutRate="1" frameRate="25"><BaseURL>https://r1---sn-ci5gup-qxas.googlevideo.com/videoplayback?expire=1625506969&amp;ei=OfDiYMPTE5KOmgfBs6LACA&amp;ip=122.161.68.8&amp;id=o-AJno_OyI_qSilg0pKp7jBgwanqzvHVJKPkIGZjQw22X8&amp;itag=243&amp;aitags=133%2C134%2C135%2C136%2C137%2C160%2C242%2C243%2C244%2C247%2C248%2C278&amp;source=youtube&amp;requiressl=yes&amp;mh=5j&amp;mm=31%2C26&amp;mn=sn-ci5gup-qxas%2Csn-cvh7knll&amp;ms=au%2Conr&amp;mv=m&amp;mvi=1&amp;pcm2cms=yes&amp;pl=20&amp;initcwndbps=1257500&amp;vprv=1&amp;mime=video%2Fwebm&amp;ns=ipuIFyzlt_lney8Fp0br1p8G&amp;gir=yes&amp;clen=28945227&amp;dur=1062.320&amp;lmt=1537379231687758&amp;mt=1625485010&amp;fvip=1&amp;keepalive=yes&amp;fexp=24001373%2C24007246&amp;c=WEB&amp;n=INvp8Xl-NYS_WS&amp;sparams=expire%2Cei%2Cip%2Cid%2Caitags%2Csource%2Crequiressl%2Cvprv%2Cmime%2Cns%2Cgir%2Cclen%2Cdur%2Clmt&amp;sig=AOq0QJ8wRAIgVuD365s1sB4Tlxo2-HZNt6nhpk2Y__h3oA_PmsDEi9kCIEnqSsdqGUD3dLB1oTgE1QeOl1NbaLqj0yAZ7foYr20d&amp;lsparams=mh%2Cmm%2Cmn%2Cms%2Cmv%2Cmvi%2Cpcm2cms%2Cpl%2Cinitcwndbps&amp;lsig=AG3C_xAwRgIhAIe-ZkVUNAh3_cNjBSy8EhGUmtNSIeH_vTTbMWzKvqVeAiEAvvO7q0GQykvj21KEthsU55H2RzLG6RpIt-jt-YAhQP0%3D&amp;ratebypass=yes</BaseURL><SegmentBase indexRange="220-3854"><Initialization range="0-219"/></SegmentBase></Representation><Representation id="242" codecs="vp9" bandwidth="148950" width="426" height="240" maxPlayoutRate="1" frameRate="25"><BaseURL>https://r1---sn-ci5gup-qxas.googlevideo.com/videoplayback?expire=1625506969&amp;ei=OfDiYMPTE5KOmgfBs6LACA&amp;ip=122.161.68.8&amp;id=o-AJno_OyI_qSilg0pKp7jBgwanqzvHVJKPkIGZjQw22X8&amp;itag=242&amp;aitags=133%2C134%2C135%2C136%2C137%2C160%2C242%2C243%2C244%2C247%2C248%2C278&amp;source=youtube&amp;requiressl=yes&amp;mh=5j&amp;mm=31%2C26&amp;mn=sn-ci5gup-qxas%2Csn-cvh7knll&amp;ms=au%2Conr&amp;mv=m&amp;mvi=1&amp;pcm2cms=yes&amp;pl=20&amp;initcwndbps=1257500&amp;vprv=1&amp;mime=video%2Fwebm&amp;ns=ipuIFyzlt_lney8Fp0br1p8G&amp;gir=yes&amp;clen=12887083&amp;dur=1062.320&amp;lmt=1537381227996991&amp;mt=1625485010&amp;fvip=1&amp;keepalive=yes&amp;fexp=24001373%2C24007246&amp;c=WEB&amp;n=INvp8Xl-NYS_WS&amp;sparams=expire%2Cei%2Cip%2Cid%2Caitags%2Csource%2Crequiressl%2Cvprv%2Cmime%2Cns%2Cgir%2Cclen%2Cdur%2Clmt&amp;sig=AOq0QJ8wRQIhAKYTyWsVbW-oY4d_Rul005RiL_YSpPfI7g0MUVmtNtNfAiAkNhCe05jN-SyHsXD2R1vIR_IpEv4WJstnR9aUkBwm6g%3D%3D&amp;lsparams=mh%2Cmm%2Cmn%2Cms%2Cmv%2Cmvi%2Cpcm2cms%2Cpl%2Cinitcwndbps&amp;lsig=AG3C_xAwRgIhAIe-ZkVUNAh3_cNjBSy8EhGUmtNSIeH_vTTbMWzKvqVeAiEAvvO7q0GQykvj21KEthsU55H2RzLG6RpIt-jt-YAhQP0%3D&amp;ratebypass=yes</BaseURL><SegmentBase indexRange="219-3762"><Initialization range="0-218"/></SegmentBase></Representation><Representation id="278" codecs="vp9" bandwidth="106898" width="256" height="144" maxPlayoutRate="1" frameRate="25"><BaseURL>https://r1---sn-ci5gup-qxas.googlevideo.com/videoplayback?expire=1625506969&amp;ei=OfDiYMPTE5KOmgfBs6LACA&amp;ip=122.161.68.8&amp;id=o-AJno_OyI_qSilg0pKp7jBgwanqzvHVJKPkIGZjQw22X8&amp;itag=278&amp;aitags=133%2C134%2C135%2C136%2C137%2C160%2C242%2C243%2C244%2C247%2C248%2C278&amp;source=youtube&amp;requiressl=yes&amp;mh=5j&amp;mm=31%2C26&amp;mn=sn-ci5gup-qxas%2Csn-cvh7knll&amp;ms=au%2Conr&amp;mv=m&amp;mvi=1&amp;pcm2cms=yes&amp;pl=20&amp;initcwndbps=1257500&amp;vprv=1&amp;mime=video%2Fwebm&amp;ns=ipuIFyzlt_lney8Fp0br1p8G&amp;gir=yes&amp;clen=11580928&amp;dur=1062.320&amp;lmt=1537381781396826&amp;mt=1625485010&amp;fvip=1&amp;keepalive=yes&amp;fexp=24001373%2C24007246&amp;c=WEB&amp;n=INvp8Xl-NYS_WS&amp;sparams=expire%2Cei%2Cip%2Cid%2Caitags%2Csource%2Crequiressl%2Cvprv%2Cmime%2Cns%2Cgir%2Cclen%2Cdur%2Clmt&amp;sig=AOq0QJ8wRgIhAPeEHHiCg1YlPMpbKVd3VciIleZTETJsCfyN-2u5khgRAiEAkL9PqnpZ6taSZ-Z0cKHNOPs3T0zJrwQQz4hEXaR9QHU%3D&amp;lsparams=mh%2Cmm%2Cmn%2Cms%2Cmv%2Cmvi%2Cpcm2cms%2Cpl%2Cinitcwndbps&amp;lsig=AG3C_xAwRgIhAIe-ZkVUNAh3_cNjBSy8EhGUmtNSIeH_vTTbMWzKvqVeAiEAvvO7q0GQykvj21KEthsU55H2RzLG6RpIt-jt-YAhQP0%3D&amp;ratebypass=yes</BaseURL><SegmentBase indexRange="219-3761"><Initialization range="0-218"/></SegmentBase></Representation></AdaptationSet><AdaptationSet id="2" mimeType="audio/mp4" startWithSAP="1" subsegmentAlignment="true"><Representation id="140" codecs="mp4a.40.2" bandwidth="128765"><AudioChannelConfiguration schemeIdUri="urn:mpeg:dash:23003:3:audio_channel_configuration:2011" value="2"/><BaseURL>https://r1---sn-ci5gup-qxas.googlevideo.com/videoplayback?expire=1625506969&amp;ei=OfDiYMPTE5KOmgfBs6LACA&amp;ip=122.161.68.8&amp;id=o-AJno_OyI_qSilg0pKp7jBgwanqzvHVJKPkIGZjQw22X8&amp;itag=140&amp;source=youtube&amp;requiressl=yes&amp;mh=5j&amp;mm=31%2C26&amp;mn=sn-ci5gup-qxas%2Csn-cvh7knll&amp;ms=au%2Conr&amp;mv=m&amp;mvi=1&amp;pcm2cms=yes&amp;pl=20&amp;initcwndbps=1257500&amp;vprv=1&amp;mime=audio%2Fmp4&amp;ns=ipuIFyzlt_lney8Fp0br1p8G&amp;gir=yes&amp;clen=16873898&amp;dur=1062.382&amp;lmt=1537374139350289&amp;mt=1625485010&amp;fvip=1&amp;keepalive=yes&amp;fexp=24001373%2C24007246&amp;c=WEB&amp;n=INvp8Xl-NYS_WS&amp;sparams=expire%2Cei%2Cip%2Cid%2Citag%2Csource%2Crequiressl%2Cvprv%2Cmime%2Cns%2Cgir%2Cclen%2Cdur%2Clmt&amp;sig=AOq0QJ8wRAIgFxlr3cR3bUjb-eRHQoEPLL9JIgENwN0nJBWwVdLPoW4CIEh8flQmJOlR5Dfs-kt4BxnTNmM_u0emL5xiqjyuq3x5&amp;lsparams=mh%2Cmm%2Cmn%2Cms%2Cmv%2Cmvi%2Cpcm2cms%2Cpl%2Cinitcwndbps&amp;lsig=AG3C_xAwRgIhAIe-ZkVUNAh3_cNjBSy8EhGUmtNSIeH_vTTbMWzKvqVeAiEAvvO7q0GQykvj21KEthsU55H2RzLG6RpIt-jt-YAhQP0%3D&amp;ratebypass=yes</BaseURL><SegmentBase indexRange="592-1907"><Initialization range="0-591"/></SegmentBase></Representation></AdaptationSet><AdaptationSet id="3" mimeType="audio/webm" startWithSAP="1" subsegmentAlignment="true"><Representation id="249" codecs="opus" bandwidth="58295"><AudioChannelConfiguration schemeIdUri="urn:mpeg:dash:23003:3:audio_channel_configuration:2011" value="2"/><BaseURL>https://r1---sn-ci5gup-qxas.googlevideo.com/videoplayback?expire=1625506969&amp;ei=OfDiYMPTE5KOmgfBs6LACA&amp;ip=122.161.68.8&amp;id=o-AJno_OyI_qSilg0pKp7jBgwanqzvHVJKPkIGZjQw22X8&amp;itag=249&amp;source=youtube&amp;requiressl=yes&amp;mh=5j&amp;mm=31%2C26&amp;mn=sn-ci5gup-qxas%2Csn-cvh7knll&amp;ms=au%2Conr&amp;mv=m&amp;mvi=1&amp;pcm2cms=yes&amp;pl=20&amp;initcwndbps=1257500&amp;vprv=1&amp;mime=audio%2Fwebm&amp;ns=ipuIFyzlt_lney8Fp0br1p8G&amp;gir=yes&amp;clen=6650236&amp;dur=1062.341&amp;lmt=1537384611923757&amp;mt=1625485010&amp;fvip=1&amp;keepalive=yes&amp;fexp=24001373%2C24007246&amp;c=WEB&amp;n=INvp8Xl-NYS_WS&amp;sparams=expire%2Cei%2Cip%2Cid%2Citag%2Csource%2Crequiressl%2Cvprv%2Cmime%2Cns%2Cgir%2Cclen%2Cdur%2Clmt&amp;sig=AOq0QJ8wRQIhAIzlrZOXibXhF5L8jpWVwe1yDvwL4vexDIVT01ZguVVfAiAoQEdKbB3Xl2ItvRLj-4WoTRKnK7CpfuPk1I9Jk9g1AA%3D%3D&amp;lsparams=mh%2Cmm%2Cmn%2Cms%2Cmv%2Cmvi%2Cpcm2cms%2Cpl%2Cinitcwndbps&amp;lsig=AG3C_xAwRgIhAIe-ZkVUNAh3_cNjBSy8EhGUmtNSIeH_vTTbMWzKvqVeAiEAvvO7q0GQykvj21KEthsU55H2RzLG6RpIt-jt-YAhQP0%3D&amp;ratebypass=yes</BaseURL><SegmentBase indexRange="266-2080"><Initialization range="0-265"/></SegmentBase></Representation><Representation id="250" codecs="opus" bandwidth="75724"><AudioChannelConfiguration schemeIdUri="urn:mpeg:dash:23003:3:audio_channel_configuration:2011" value="2"/><BaseURL>https://r1---sn-ci5gup-qxas.googlevideo.com/videoplayback?expire=1625506969&amp;ei=OfDiYMPTE5KOmgfBs6LACA&amp;ip=122.161.68.8&amp;id=o-AJno_OyI_qSilg0pKp7jBgwanqzvHVJKPkIGZjQw22X8&amp;itag=250&amp;source=youtube&amp;requiressl=yes&amp;mh=5j&amp;mm=31%2C26&amp;mn=sn-ci5gup-qxas%2Csn-cvh7knll&amp;ms=au%2Conr&amp;mv=m&amp;mvi=1&amp;pcm2cms=yes&amp;pl=20&amp;initcwndbps=1257500&amp;vprv=1&amp;mime=audio%2Fwebm&amp;ns=ipuIFyzlt_lney8Fp0br1p8G&amp;gir=yes&amp;clen=9286449&amp;dur=1062.341&amp;lmt=1537384612143133&amp;mt=1625485010&amp;fvip=1&amp;keepalive=yes&amp;fexp=24001373%2C24007246&amp;c=WEB&amp;n=INvp8Xl-NYS_WS&amp;sparams=expire%2Cei%2Cip%2Cid%2Citag%2Csource%2Crequiressl%2Cvprv%2Cmime%2Cns%2Cgir%2Cclen%2Cdur%2Clmt&amp;sig=AOq0QJ8wRAIgZ-Gq0H_tZC_c4MgE0_089-_uFUfh0aBHgmeSbNkLM0oCIAQtdMdZh_1ncPkZVPCPbsGBmzdokizclZ1JrEnrnCoR&amp;lsparams=mh%2Cmm%2Cmn%2Cms%2Cmv%2Cmvi%2Cpcm2cms%2Cpl%2Cinitcwndbps&amp;lsig=AG3C_xAwRgIhAIe-ZkVUNAh3_cNjBSy8EhGUmtNSIeH_vTTbMWzKvqVeAiEAvvO7q0GQykvj21KEthsU55H2RzLG6RpIt-jt-YAhQP0%3D&amp;ratebypass=yes</BaseURL><SegmentBase indexRange="266-2080"><Initialization range="0-265"/></SegmentBase></Representation><Representation id="251" codecs="opus" bandwidth="130337"><AudioChannelConfiguration schemeIdUri="urn:mpeg:dash:23003:3:audio_channel_configuration:2011" value="2"/><BaseURL>https://r1---sn-ci5gup-qxas.googlevideo.com/videoplayback?expire=1625506969&amp;ei=OfDiYMPTE5KOmgfBs6LACA&amp;ip=122.161.68.8&amp;id=o-AJno_OyI_qSilg0pKp7jBgwanqzvHVJKPkIGZjQw22X8&amp;itag=251&amp;source=youtube&amp;requiressl=yes&amp;mh=5j&amp;mm=31%2C26&amp;mn=sn-ci5gup-qxas%2Csn-cvh7knll&amp;ms=au%2Conr&amp;mv=m&amp;mvi=1&amp;pcm2cms=yes&amp;pl=20&amp;initcwndbps=1257500&amp;vprv=1&amp;mime=audio%2Fwebm&amp;ns=ipuIFyzlt_lney8Fp0br1p8G&amp;gir=yes&amp;clen=15929323&amp;dur=1062.341&amp;lmt=1537384613345519&amp;mt=1625485010&amp;fvip=1&amp;keepalive=yes&amp;fexp=24001373%2C24007246&amp;c=WEB&amp;n=INvp8Xl-NYS_WS&amp;sparams=expire%2Cei%2Cip%2Cid%2Citag%2Csource%2Crequiressl%2Cvprv%2Cmime%2Cns%2Cgir%2Cclen%2Cdur%2Clmt&amp;sig=AOq0QJ8wRgIhAODD_Iz677WJZ6WzdFPX6XAnyJTkVBbLFXWqsYO3Df13AiEAmHh76z0VS0VTMdrJhzOG02rS2BSBZQ3_eu-8F-Jvo4Y%3D&amp;lsparams=mh%2Cmm%2Cmn%2Cms%2Cmv%2Cmvi%2Cpcm2cms%2Cpl%2Cinitcwndbps&amp;lsig=AG3C_xAwRgIhAIe-ZkVUNAh3_cNjBSy8EhGUmtNSIeH_vTTbMWzKvqVeAiEAvvO7q0GQykvj21KEthsU55H2RzLG6RpIt-jt-YAhQP0%3D&amp;ratebypass=yes</BaseURL><SegmentBase indexRange="266-2081"><Initialization range="0-265"/></SegmentBase></Representation></AdaptationSet></Period></MPD>